walledeval/__init__.py
walledeval/attacks/__init__.py
walledeval/attacks/core.py
walledeval/attacks/mutators/__init__.py
walledeval/attacks/mutators/artprompt.py
walledeval/attacks/mutators/cipher.py
walledeval/attacks/mutators/core.py
walledeval/attacks/mutators/generative.py
walledeval/attacks/mutators/rule.py
walledeval/attacks/mutators/translation.py
walledeval/attacks/wildteaming.py
walledeval/constants/__init__.py
walledeval/data/__init__.py
walledeval/data/core.py
walledeval/judge/__init__.py
walledeval/judge/classifiers/__init__.py
walledeval/judge/code.py
walledeval/judge/core.py
walledeval/judge/huggingface/__init__.py
walledeval/judge/huggingface/core.py
walledeval/judge/huggingface/models.py
walledeval/judge/lionguard/__init__.py
walledeval/judge/lionguard/presets/binary.yaml
walledeval/judge/lionguard/presets/harassment.yaml
walledeval/judge/lionguard/presets/hateful.yaml
walledeval/judge/lionguard/presets/public_harm.yaml
walledeval/judge/lionguard/presets/self_harm.yaml
walledeval/judge/lionguard/presets/sexual.yaml
walledeval/judge/lionguard/presets/toxic.yaml
walledeval/judge/lionguard/presets/violent.yaml
walledeval/judge/llm/__init__.py
walledeval/judge/llm/core.py
walledeval/judge/llm/guard.py
walledeval/judge/llm/llamaguard.py
walledeval/judge/llm/question.py
walledeval/judge/llm/toxicity.py
walledeval/judge/llm/walledguard.py
walledeval/judge/mcq.py
walledeval/judge/string/__init__.py
walledeval/judge/string/presets/lapid2023open.yaml
walledeval/judge/string/presets/liu2024autodan-implementation.yaml
walledeval/judge/string/presets/liu2024autodan-keyword.yaml
walledeval/judge/string/presets/zhang2024intention-keyword.yaml
walledeval/judge/string/presets/zou2023universal-closed.yaml
walledeval/judge/string/presets/zou2023universal-demo.yaml
walledeval/judge/string/presets/zou2023universal-individual.yaml
walledeval/judge/string/presets/zou2023universal-transfer.yaml
walledeval/judge/string/presets/zou2023universal.yaml
walledeval-0.2.1.dist-info/LICENSE
walledeval-0.2.1.dist-info/METADATA
walledeval-0.2.1.dist-info/WHEEL
walledeval-0.2.1.dist-info/RECORD
