Metadata-Version: 2.1
Name: walledeval
Version: 0.2.1
Summary: An open-source toolkit to test LLMs against jailbreaks and unprecedented harms.
Home-page: https://github.com/walledai/walledeval
License: MIT
Keywords: NLP,deep learning,transformer,language model,jailbreaking,red-teaming
Author: Rishabh Bhardwaj
Requires-Python: >=3.10,<4.0
Classifier: Development Status :: 1 - Planning
Classifier: Intended Audience :: Science/Research
Classifier: License :: OSI Approved :: MIT License
Classifier: Operating System :: OS Independent
Classifier: Programming Language :: Python
Classifier: Programming Language :: Python :: 3
Classifier: Programming Language :: Python :: 3.10
Classifier: Programming Language :: Python :: 3.11
Classifier: Programming Language :: Python :: 3.12
Classifier: Topic :: Scientific/Engineering :: Artificial Intelligence
Requires-Dist: accelerate (>=0.31.0,<0.32.0)
Requires-Dist: anthropic (>=0.25.6,<0.26.0)
Requires-Dist: art (>=6.2,<7.0)
Requires-Dist: codeshield (>=1.0.1,<2.0.0)
Requires-Dist: cohere (>=5.5.8,<6.0.0)
Requires-Dist: datasets (>=2.19.0,<3.0.0)
Requires-Dist: google-generativeai (>=0.5.2,<0.6.0)
Requires-Dist: groq (>=0.9.0,<0.10.0)
Requires-Dist: inflect (>=7.3.1,<8.0.0)
Requires-Dist: numpy (<2)
Requires-Dist: onnxruntime (>=1.18.1,<2.0.0)
Requires-Dist: openai (>=1.23.6,<2.0.0)
Requires-Dist: pydantic (>=2.7.1,<3.0.0)
Requires-Dist: python-dotenv (>=1.0.1,<2.0.0)
Requires-Dist: pyyaml (>=6.0,<7.0)
Requires-Dist: scikit-learn (>=1.5.0,<2.0.0)
Requires-Dist: together (>=1.2.1,<2.0.0)
Requires-Dist: transformers (>=4.40.1,<5.0.0)
Requires-Dist: xgboost (>=2.1.0,<3.0.0)
Project-URL: Bug Tracker, https://github.com/walledai/walledeval/issues
Project-URL: Repository, https://github.com/walledai/walledeval
